{
"index": "CorpusMR",
"niveau": "5",
"dossier": "مرشدي في اللغة العربية",
"titre": "الأقمار الصناعية",
"contenu": "توالى أحول جود مدار احوال خريطة كشف قارة أمى صناعية ونى وضع ذل عملية عد عبر حوال أولى في أولي بعد مكالمة عن عين صناعي أفضل صانع آلى أنى وهى وهي جوي وجود ذال فضاء أرضة تكشف وعد مسح أول هاتفي بيا قمر أقدم جيح تم جوية عملي تي وعى كم آن على وفى أحمل بين إراض حولاء معدن أم ما ساعد أن إنس قمراء صناع عبرة دراسة ماكن فلك إنسان كون حمل نافعة أرض ناع قدم سوعد عنى هاتفية تنوع أقمر ناس تقدم أجيح نوع طقس ضاع وكم مدرى لكي ذلك اقمار اتصال فائدة تام ضع إطلاع تحمل استخدم إطلاق ضل ولى ولي وأى فضل عان صورة هي عالم مماثلة عدى مكان عام امتلأ أكشف أما رامج متنوعة برنامج عاد التي نجاح حال ألي حول "
}