{
"index": "CorpusMR",
"niveau": "5",
"dossier": "مرشدي في اللغة العربية",
"titre": "شارلي شابلن",
"contenu": "شهرة ألمي ودأ بار طفولة ألمى تركى شخصية سنة ونى فنان ذل عد ازداد نيه متحدة مان كبار فن أخذى أولى في بعد أولي شال ركا سنى آلى أنى وهى أخذ رك أنه وهي همى مرح ذال لهى وهم قف ركي أنهي مضحكة وعد شخصي أنهى تر أول سيار منتج أهم عديد عنوان مين لام لاه كبيرة داء تي ورك آن على مثل ليم وفى أحمل انتشر والف رأى سن تفوق قامى زمان ولاية عمل لم طفل أرك أن له تار شريط أري أرى عالمي عالمية بارى مخرج وتر ورى وري حمل سبع هام أليم وقف خشبة قدم من عنو قاف وسى نهى نهي خذا أركى ذلك أركي عصري عامل خذ عمال ترك رئي شالي منى وله ولى وأى ولي أسلوب قام مسرح انتقد كبير ألام ناه لما هم فوق فاق شهر جولة سيارة ممثل عدى بدأ بعدما عصرية لمى مات لمي قفى مثال ألم مضحك عدم عاد سباق التي ألي "
}